xontrib_avox_poetry/__init__.py
xontrib_avox_poetry/loader.py
xontrib_avox_poetry/utils.py
xontrib_avox_poetry/venv.py
xontrib_avox_poetry/venv_poetry.py
xontrib_avox_poetry-0.3.3.dist-info/entry_points.txt
xontrib_avox_poetry-0.3.3.dist-info/LICENSE
xontrib_avox_poetry-0.3.3.dist-info/WHEEL
xontrib_avox_poetry-0.3.3.dist-info/METADATA
xontrib_avox_poetry-0.3.3.dist-info/RECORD
